bearing/__init__.py
bearing/__version__.py
bearing/geometry/__init__.py
bearing/geometry/point.py
bearing/geospatial/__init__.py
bearing-0.0.0.dist-info/METADATA
bearing-0.0.0.dist-info/WHEEL
bearing-0.0.0.dist-info/top_level.txt
bearing-0.0.0.dist-info/zip-safe
bearing-0.0.0.dist-info/RECORD
