Metadata-Version: 2.1
Name: bearing
Version: 0.0.0
Summary: Starling Bearing is a Spatial Python Framework
Home-page: https://www.starling.associates
Download-URL: https://www.starling.associates
Author: Lars van Vianen
Author-email: lars@starling.associates
Maintainer: Starling Associates
Maintainer-email: info@starling.associates
License: MIT
Project-URL: documentation, https://bearing.pypa.io/
Project-URL: repository, https://github.com/starling-cloud/bearing
Keywords: starling,bearing,geometry,geospatial
Classifier: Development Status :: 1 - Planning
Classifier: Intended Audience :: Developers
Classifier: License :: OSI Approved :: MIT License
Classifier: Natural Language :: English
Classifier: Operating System :: OS Independent
Classifier: Programming Language :: Python :: 3 :: Only
Classifier: Topic :: Scientific/Engineering
Classifier: Topic :: Software Development :: Libraries
Requires-Python: >=3.7
